miniscons/__init__.py
miniscons/build.py
miniscons/compiler.py
miniscons/constants.py
miniscons/containers.py
miniscons/environment.py
miniscons/flag.py
miniscons/routine.py
miniscons/script.py
miniscons/target.py
miniscons/tasks.py
miniscons-0.13.0.dist-info/METADATA
miniscons-0.13.0.dist-info/WHEEL
miniscons-0.13.0.dist-info/licenses/LICENSE.md
miniscons-0.13.0.dist-info/RECORD
